doculite.py
docu_lite-1.5.1.dist-info/licenses/LICENSE
docu_lite-1.5.1.dist-info/METADATA
docu_lite-1.5.1.dist-info/WHEEL
docu_lite-1.5.1.dist-info/entry_points.txt
docu_lite-1.5.1.dist-info/top_level.txt
docu_lite-1.5.1.dist-info/RECORD
